django_zappa/__init__.py
django_zappa/handler.py
django_zappa/middleware.py
django_zappa/tests.py
django_zappa/urls.py
django_zappa/management/__init__.py
django_zappa/management/commands/__init__.py
django_zappa/management/commands/deploy.py
django_zappa/management/commands/invoke.py
django_zappa/management/commands/rollback.py
django_zappa/management/commands/tail.py
django_zappa/management/commands/update.py
django_zappa/management/commands/zappa_command.py
django_zappa-0.13.1.dist-info/DESCRIPTION.rst
django_zappa-0.13.1.dist-info/METADATA
django_zappa-0.13.1.dist-info/RECORD
django_zappa-0.13.1.dist-info/WHEEL
django_zappa-0.13.1.dist-info/metadata.json
django_zappa-0.13.1.dist-info/pbr.json
django_zappa-0.13.1.dist-info/top_level.txt
