Metadata-Version: 2.0
Name: django-zappa
Version: 0.13.1
Summary: Serverless Django With AWS Lambda + API Gateway
Home-page: https://github.com/Miserlou/django-zappa
Author: Rich Jones
Author-email: rich@openwatch.net
License: MIT License
Download-URL: https://github.com/Miserlou/django-zappa
Platform: UNKNOWN
Classifier: Environment :: Console
Classifier: Environment :: Web Environment
Classifier: Framework :: Django
Classifier: Intended Audience :: Developers
Classifier: License :: OSI Approved :: Apache Software License
Classifier: Operating System :: OS Independent
Classifier: Programming Language :: Python
Classifier: Programming Language :: Python :: 2.7
Classifier: Programming Language :: Python :: 3.3
Classifier: Programming Language :: Python :: 3.4
Classifier: Programming Language :: Python :: 3.5
Classifier: Topic :: Internet :: WWW/HTTP
Classifier: Topic :: Internet :: WWW/HTTP :: Dynamic Content
Requires-Dist: Django (>=1.8)
Requires-Dist: base58 (==0.2.2)
Requires-Dist: mysql-connector-python-rf (==2.1.3)
Requires-Dist: requests (>=2.9.1)
Requires-Dist: wheel (==0.29.0)
Requires-Dist: zappa (==0.17.4)
